[
  { "name": "facebook_zstd", "url": "https://github.com/facebook/zstd" },
  { "name": "flex", "url": "https://github.com/uiuc-arc/flex" },
  { "name": "fmtlib_fmt", "url": "https://github.com/fmtlib/fmt" },
  { "name": "gluetest", "url": "https://github.com/seal-research/gluetest" },
  { "name": "grpc_grpc-go", "url": "https://github.com/grpc/grpc-go" },
  { "name": "iamkun_dayjs", "url": "https://github.com/iamkun/dayjs" },
  { "name": "jqlang_jq", "url": "https://github.com/jqlang/jq" },
  { "name": "mockito_mockito", "url": "https://github.com/mockito/mockito" },
  { "name": "mui_material-ui", "url": "https://github.com/mui/material-ui" },
  { "name": "nlohmann_json", "url": "https://github.com/nlohmann/json" },
  { "name": "nushell_nushell", "url": "https://github.com/nushell/nushell" },
  { "name": "ponylang_ponyc", "url": "https://github.com/ponylang/ponyc" },
  { "name": "probfuzz", "url": "https://github.com/uiuc-arc/probfuzz" },
  { "name": "rayon-rs_rayon", "url": "https://github.com/rayon-rs/rayon" },
  { "name": "rfuse", "url": "https://github.com/snu-csl/rfuse" },
  { "name": "serde-rs_serde", "url": "https://github.com/serde-rs/serde" },
  { "name": "sharkdp_bat", "url": "https://github.com/sharkdp/bat" },
  { "name": "sharkdp_fd", "url": "https://github.com/sharkdp/fd" },
  { "name": "simdjson_simdjson", "url": "https://github.com/simdjson/simdjson" },
  { "name": "sixthsense", "url": "https://github.com/uiuc-arc/sixthsense" },
  { "name": "sveltejs_svelte", "url": "https://github.com/sveltejs/svelte" },
  { "name": "tokio-rs_bytes", "url": "https://github.com/tokio-rs/bytes" },
  { "name": "tokio-rs_tokio", "url": "https://github.com/tokio-rs/tokio" },
  { "name": "tokio-rs_tracing", "url": "https://github.com/tokio-rs/tracing" },
  { "name": "vuejs_core", "url": "https://github.com/vuejs/core" },
  { "name": "yhirose_cpp-httplib", "url": "https://github.com/yhirose/cpp-httplib" },
  { "name": "zeromicro_go-zero", "url": "https://github.com/zeromicro/go-zero" }
]